a_texam-1.1.dist-info/licenses/LICENSE
atexam/__init__.py
atexam/__main__.py
atexam/app.py
atexam/models.py
atexam/instance/database.db
atexam/static/ban.jpg
atexam/static/styles.css
atexam/static/t.jpg
atexam/templates/about.html
atexam/templates/add_question.html
atexam/templates/add_test.html
atexam/templates/admin_login.html
atexam/templates/admin_result_detail.html
atexam/templates/admin_results.html
atexam/templates/admin_tests.html
atexam/templates/admin_users.html
atexam/templates/banned.html
atexam/templates/edit_question.html
atexam/templates/edit_test.html
atexam/templates/history.html
atexam/templates/index.html
atexam/templates/login.html
atexam/templates/register.html
atexam/templates/registration_requests.html
atexam/templates/result.html
atexam/templates/test.html
atexam/templates/test_questions.html
a_texam-1.1.dist-info/METADATA
a_texam-1.1.dist-info/WHEEL
a_texam-1.1.dist-info/entry_points.txt
a_texam-1.1.dist-info/top_level.txt
a_texam-1.1.dist-info/RECORD
